dawshs_jff/__init__.py
dawshs_jff/schemas/config.py
dawshs_jff/scripts/jff.py
dawshs_jff/utils/captcha.py
dawshs_jff/v12/__init__.py
dawshs_jff/v12/constants.py
dawshs_jff/v12/encryption.py
dawshs_jff/v12/hashes.py
dawshs_jff/v12/request.py
dawshs_jff/v12/samples.py
dawshs_jff-0.1.1.dist-info/LICENSE
dawshs_jff-0.1.1.dist-info/METADATA
dawshs_jff-0.1.1.dist-info/WHEEL
dawshs_jff-0.1.1.dist-info/entry_points.txt
dawshs_jff-0.1.1.dist-info/top_level.txt
dawshs_jff-0.1.1.dist-info/RECORD
