Metadata-Version: 2.2
Name: dawshs_jff
Version: 0.1.1
Summary: Dawsh's Just For Fun project
License:             DO WHAT THE FUCK YOU WANT TO PUBLIC LICENSE
License-File: LICENSE
Requires-Dist: httpx~=0.27.0
Requires-Dist: tzlocal~=5.2
Requires-Dist: opencv-python~=4.10.0.82
Requires-Dist: numpy~=1.26.4
Requires-Dist: pytesseract~=0.3.10
Requires-Dist: pydantic~=2.10.6
Requires-Dist: pycryptodome~=3.20.0
